{
    "images": [
        {
            "width": 827,
            "height": 1170,
            "id": 0,
            "file_name": "8d8b9b6b-1.jpg"
        },
        {
            "width": 827,
            "height": 1170,
            "id": 1,
            "file_name": "598e3d7f-2.jpg"
        },
        {
            "width": 827,
            "height": 1170,
            "id": 2,
            "file_name": "4c205a8a-3.jpg"
        },
        {
            "width": 827,
            "height": 1170,
            "id": 3,
            "file_name": "5f25df97-4.jpg"
        },
        {
            "width": 827,
            "height": 1170,
            "id": 4,
            "file_name": "d5bc2db7-5.jpg"
        },
        {
            "width": 827,
            "height": 1170,
            "id": 5,
            "file_name": "8149563f-6.jpg"
        },
        {
            "width": 827,
            "height": 1170,
            "id": 6,
            "file_name": "04464695-7.jpg"
        },
        {
            "width": 827,
            "height": 1170,
            "id": 7,
            "file_name": "8c1ffa8f-8.jpg"
        },
        {
            "width": 827,
            "height": 1170,
            "id": 8,
            "file_name": "6e3c4424-9.jpg"
        },
        {
            "width": 827,
            "height": 1170,
            "id": 9,
            "file_name": "6b5f29a0-10.jpg"
        },
        {
            "width": 827,
            "height": 1170,
            "id": 10,
            "file_name": "4ca482bc-11.jpg"
        },
        {
            "width": 827,
            "height": 1170,
            "id": 11,
            "file_name": "3165f223-12.jpg"
        },
        {
            "width": 827,
            "height": 1170,
            "id": 12,
            "file_name": "3d13b5c2-13.jpg"
        },
        {
            "width": 827,
            "height": 1170,
            "id": 13,
            "file_name": "da78faf0-14.jpg"
        },
        {
            "width": 827,
            "height": 1170,
            "id": 14,
            "file_name": "8d492041-15.jpg"
        },
        {
            "width": 827,
            "height": 1170,
            "id": 15,
            "file_name": "5e6ec920-16.jpg"
        },
        {
            "width": 827,
            "height": 1170,
            "id": 16,
            "file_name": "39b2a260-17.jpg"
        },
        {
            "width": 827,
            "height": 1170,
            "id": 17,
            "file_name": "fa58ace1-18.jpg"
        },
        {
            "width": 827,
            "height": 1170,
            "id": 18,
            "file_name": "776a5688-19.jpg"
        },
        {
            "width": 827,
            "height": 1170,
            "id": 19,
            "file_name": "b7f5df54-20.jpg"
        },
        {
            "width": 827,
            "height": 1170,
            "id": 20,
            "file_name": "b26af411-21.jpg"
        },
        {
            "width": 827,
            "height": 1170,
            "id": 21,
            "file_name": "a90a158d-22.jpg"
        },
        {
            "width": 827,
            "height": 1170,
            "id": 22,
            "file_name": "74df1b77-23.jpg"
        }
    ],
    "categories": [
        {
            "id": 0,
            "name": "aside"
        },
        {
            "id": 1,
            "name": "contents"
        },
        {
            "id": 2,
            "name": "doc_title"
        },
        {
            "id": 3,
            "name": "equation"
        },
        {
            "id": 4,
            "name": "equation_number"
        },
        {
            "id": 5,
            "name": "figure"
        },
        {
            "id": 6,
            "name": "figure_title"
        },
        {
            "id": 7,
            "name": "footer"
        },
        {
            "id": 8,
            "name": "footnote"
        },
        {
            "id": 9,
            "name": "header"
        },
        {
            "id": 10,
            "name": "info"
        },
        {
            "id": 11,
            "name": "page_number"
        },
        {
            "id": 12,
            "name": "reference"
        },
        {
            "id": 13,
            "name": "seal"
        },
        {
            "id": 14,
            "name": "supplement"
        },
        {
            "id": 15,
            "name": "table"
        },
        {
            "id": 16,
            "name": "table_title"
        },
        {
            "id": 17,
            "name": "text"
        },
        {
            "id": 18,
            "name": "text_title"
        }
    ],
    "annotations": [
        {
            "id": 0,
            "image_id": 0,
            "category_id": 9,
            "segmentation": [],
            "bbox": [
                99.57446808510639,
                64.72340425531915,
                175.91489361702122,
                19.914893617021274
            ],
            "ignore": 0,
            "iscrowd": 0,
            "area": 3503.3263920325926
        },
        {
            "id": 1,
            "image_id": 0,
            "category_id": 9,
            "segmentation": [],
            "bbox": [
                315.3191489361702,
                114.51063829787233,
                200.8085106382979,
                24.89361702127662
            ],
            "ignore": 0,
            "iscrowd": 0,
            "area": 4998.8501584427395
        },
        {
            "id": 2,
            "image_id": 0,
            "category_id": 9,
            "segmentation": [],
            "bbox": [
                101.23404255319149,
                202.46808510638297,
                288.7659574468085,
                370.0851063829788
            ],
            "ignore": 0,
            "iscrowd": 0,
            "area": 106867.98008148484
        },
        {
            "id": 3,
            "image_id": 0,
            "category_id": 9,
            "segmentation": [],
            "bbox": [
                517.787234042553,
                151.02127659574467,
                217.4042553191491,
                41.489361702127596
            ],
            "ignore": 0,
            "iscrowd": 0,
            "area": 9019.963784517873
        },
        {
            "id": 4,
            "image_id": 0,
            "category_id": 13,
            "segmentation": [],
            "bbox": [
                127.7872340425532,
                109.53191489361703,
                92.93617021276597,
                71.36170212765958
            ],
            "ignore": 0,
            "iscrowd": 0,
            "area": 6632.083295608874
        },
        {
            "id": 5,
            "image_id": 0,
            "category_id": 13,
            "segmentation": [],
            "bbox": [
                630.6382978723403,
                69.70212765957444,
                53.106382978723126,
                58.08510638297873
            ],
            "ignore": 0,
            "iscrowd": 0,
            "area": 3084.6899049343438
        },
        {
            "id": 6,
            "image_id": 0,
            "category_id": 9,
            "segmentation": [],
            "bbox": [
                459.70212765957444,
                562.5957446808511,
                224.0425531914894,
                16.595744680851077
            ],
            "ignore": 0,
            "iscrowd": 0,
            "area": 3718.1530104119543
        },
        {
            "id": 7,
            "image_id": 0,
            "category_id": 5,
            "segmentation": [],
            "bbox": [
                431.74930063247916,
                657.151451256107,
                295.40425531914906,
                233.1407245098158
            ],
            "ignore": 0,
            "iscrowd": 0,
            "area": 68870.76210838903
        },
        {
            "id": 8,
            "image_id": 0,
            "category_id": 18,
            "segmentation": [],
            "bbox": [
                97.91489361702128,
                585.8297872340424,
                94.59574468085106,
                24.893617021276658
            ],
            "ignore": 0,
            "iscrowd": 0,
            "area": 2354.830239927575
        },
        {
            "id": 9,
            "image_id": 0,
            "category_id": 18,
            "segmentation": [],
            "bbox": [
                97.91489361702129,
                660.5106382978722,
                58.08510638297872,
                14.936170212765914
            ],
            "ignore": 0,
            "iscrowd": 0,
            "area": 867.569035762786
        },
        {
            "id": 10,
            "image_id": 0,
            "category_id": 17,
            "segmentation": [],
            "bbox": [
                101.23404255319147,
                614.0425531914892,
                297.0638297872339,
                38.17021276595762
            ],
            "ignore": 0,
            "iscrowd": 0,
            "area": 11338.989588048937
        },
        {
            "id": 11,
            "image_id": 0,
            "category_id": 17,
            "segmentation": [],
            "bbox": [
                99.57446808510642,
                675.4468085106381,
                298.72340425531934,
                310.340425531915
            ],
            "ignore": 0,
            "iscrowd": 0,
            "area": 92705.94839293807
        },
        {
            "id": 12,
            "image_id": 0,
            "category_id": 0,
            "segmentation": [],
            "bbox": [
                74.68085106382979,
                921.0638297872341,
                21.574468085106368,
                122.80851063829779
            ],
            "ignore": 0,
            "iscrowd": 0,
            "area": 2649.5282933454014
        },
        {
            "id": 13,
            "image_id": 1,
            "category_id": 9,
            "segmentation": [],
            "bbox": [
                84.63829787234043,
                56.42553191489362,
                112.85106382978724,
                19.914893617021274
            ],
            "ignore": 0,
            "iscrowd": 0,
            "area": 2247.41693073789
        },
        {
            "id": 14,
            "image_id": 1,
            "category_id": 9,
            "segmentation": [],
            "bbox": [
                321.95744680851067,
                46.468085106382986,
                182.55319148936167,
                28.212765957446805
            ],
            "ignore": 0,
            "iscrowd": 0,
            "area": 5150.33046627433
        },
        {
            "id": 15,
            "image_id": 1,
            "category_id": 11,
            "segmentation": [],
            "bbox": [
                404.93617021276594,
                1075.404255319149,
                14.936170212765939,
                18.255319148936245
            ],
            "ignore": 0,
            "iscrowd": 0,
            "area": 272.66455409687717
        },
        {
            "id": 16,
            "image_id": 1,
            "category_id": 11,
            "segmentation": [],
            "bbox": [
                692.0425531914894,
                54.765957446808514,
                48.12765957446809,
                19.914893617021274
            ],
            "ignore": 0,
            "iscrowd": 0,
            "area": 958.4572204617474
        },
        {
            "id": 17,
            "image_id": 1,
            "category_id": 17,
            "segmentation": [],
            "bbox": [
                89.61702127659574,
                87.95744680851062,
                650.5531914893617,
                962.5531914893617
            ],
            "ignore": 0,
            "iscrowd": 0,
            "area": 626192.0507016749
        },
        {
            "id": 18,
            "image_id": 2,
            "category_id": 9,
            "segmentation": [],
            "bbox": [
                84.63829787234043,
                56.42553191489362,
                112.85106382978724,
                19.914893617021274
            ],
            "ignore": 0,
            "iscrowd": 0,
            "area": 2247.41693073789
        },
        {
            "id": 19,
            "image_id": 2,
            "category_id": 9,
            "segmentation": [],
            "bbox": [
                321.95744680851067,
                46.468085106382986,
                182.55319148936167,
                28.212765957446805
            ],
            "ignore": 0,
            "iscrowd": 0,
            "area": 5150.33046627433
        },
        {
            "id": 20,
            "image_id": 2,
            "category_id": 11,
            "segmentation": [],
            "bbox": [
                404.93617021276594,
                1075.404255319149,
                14.936170212765939,
                18.255319148936245
            ],
            "ignore": 0,
            "iscrowd": 0,
            "area": 272.66455409687717
        },
        {
            "id": 21,
            "image_id": 2,
            "category_id": 11,
            "segmentation": [],
            "bbox": [
                692.0425531914894,
                54.765957446808514,
                48.12765957446809,
                19.914893617021274
            ],
            "ignore": 0,
            "iscrowd": 0,
            "area": 958.4572204617474
        },
        {
            "id": 22,
            "image_id": 2,
            "category_id": 17,
            "segmentation": [],
            "bbox": [
                89.61702127659574,
                87.95744680851062,
                650.5531914893617,
                962.5531914893617
            ],
            "ignore": 0,
            "iscrowd": 0,
            "area": 626192.0507016749
        },
        {
            "id": 23,
            "image_id": 3,
            "category_id": 9,
            "segmentation": [],
            "bbox": [
                84.63829787234043,
                56.42553191489362,
                112.85106382978724,
                19.914893617021274
            ],
            "ignore": 0,
            "iscrowd": 0,
            "area": 2247.41693073789
        },
        {
            "id": 24,
            "image_id": 3,
            "category_id": 9,
            "segmentation": [],
            "bbox": [
                321.95744680851067,
                46.468085106382986,
                182.55319148936167,
                28.212765957446805
            ],
            "ignore": 0,
            "iscrowd": 0,
            "area": 5150.33046627433
        },
        {
            "id": 25,
            "image_id": 3,
            "category_id": 11,
            "segmentation": [],
            "bbox": [
                404.93617021276594,
                1075.404255319149,
                14.936170212765939,
                18.255319148936245
            ],
            "ignore": 0,
            "iscrowd": 0,
            "area": 272.66455409687717
        },
        {
            "id": 26,
            "image_id": 3,
            "category_id": 11,
            "segmentation": [],
            "bbox": [
                692.0425531914894,
                54.765957446808514,
                48.12765957446809,
                19.914893617021274
            ],
            "ignore": 0,
            "iscrowd": 0,
            "area": 958.4572204617474
        },
        {
            "id": 27,
            "image_id": 3,
            "category_id": 17,
            "segmentation": [],
            "bbox": [
                89.61702127659574,
                87.95744680851062,
                650.5531914893617,
                962.5531914893617
            ],
            "ignore": 0,
            "iscrowd": 0,
            "area": 626192.0507016749
        },
        {
            "id": 28,
            "image_id": 4,
            "category_id": 9,
            "segmentation": [],
            "bbox": [
                84.63829787234043,
                56.42553191489362,
                112.85106382978724,
                19.914893617021274
            ],
            "ignore": 0,
            "iscrowd": 0,
            "area": 2247.41693073789
        },
        {
            "id": 29,
            "image_id": 4,
            "category_id": 9,
            "segmentation": [],
            "bbox": [
                321.95744680851067,
                46.468085106382986,
                182.55319148936167,
                28.212765957446805
            ],
            "ignore": 0,
            "iscrowd": 0,
            "area": 5150.33046627433
        },
        {
            "id": 30,
            "image_id": 4,
            "category_id": 11,
            "segmentation": [],
            "bbox": [
                404.93617021276594,
                1075.404255319149,
                14.936170212765939,
                18.255319148936245
            ],
            "ignore": 0,
            "iscrowd": 0,
            "area": 272.66455409687717
        },
        {
            "id": 31,
            "image_id": 4,
            "category_id": 11,
            "segmentation": [],
            "bbox": [
                692.0425531914894,
                54.765957446808514,
                48.12765957446809,
                19.914893617021274
            ],
            "ignore": 0,
            "iscrowd": 0,
            "area": 958.4572204617474
        },
        {
            "id": 32,
            "image_id": 4,
            "category_id": 17,
            "segmentation": [],
            "bbox": [
                89.6170212765958,
                87.95744680851062,
                650.5531914893617,
                371.7446808510638
            ],
            "ignore": 0,
            "iscrowd": 0,
            "area": 241839.68854685372
        },
        {
            "id": 33,
            "image_id": 5,
            "category_id": 9,
            "segmentation": [],
            "bbox": [
                87.95744680851062,
                54.765957446808514,
                107.87234042553193,
                19.914893617021274
            ],
            "ignore": 0,
            "iscrowd": 0,
            "area": 2148.2661837935716
        },
        {
            "id": 34,
            "image_id": 5,
            "category_id": 9,
            "segmentation": [],
            "bbox": [
                358.46808510638294,
                46.468085106382986,
                104.55319148936174,
                24.893617021276587
            ],
            "ignore": 0,
            "iscrowd": 0,
            "area": 2602.7071072883655
        },
        {
            "id": 35,
            "image_id": 5,
            "category_id": 11,
            "segmentation": [],
            "bbox": [
                409.9148936170213,
                1073.744680851064,
                8.297872340425508,
                21.57446808510641
            ],
            "ignore": 0,
            "iscrowd": 0,
            "area": 179.02218198279735
        },
        {
            "id": 36,
            "image_id": 5,
            "category_id": 11,
            "segmentation": [],
            "bbox": [
                685.4042553191489,
                56.42553191489362,
                54.76595744680853,
                18.25531914893617
            ],
            "ignore": 0,
            "iscrowd": 0,
            "area": 999.7700316885472
        },
        {
            "id": 37,
            "image_id": 5,
            "category_id": 17,
            "segmentation": [],
            "bbox": [
                92.93617021276592,
                497.8723404255312,
                650.5531914893617,
                541.0212765957453
            ],
            "ignore": 0,
            "iscrowd": 0,
            "area": 351963.11815301084
        },
        {
            "id": 38,
            "image_id": 5,
            "category_id": 18,
            "segmentation": [],
            "bbox": [
                86.29787234042554,
                471.3191489361702,
                73.02127659574468,
                24.893617021276572
            ],
            "ignore": 0,
            "iscrowd": 0,
            "area": 1817.7636939791744
        },
        {
            "id": 39,
            "image_id": 5,
            "category_id": 18,
            "segmentation": [],
            "bbox": [
                89.61702127659574,
                250.595744680851,
                74.68085106382979,
                18.255319148936202
            ],
            "ignore": 0,
            "iscrowd": 0,
            "area": 1363.3227704843846
        },
        {
            "id": 40,
            "image_id": 5,
            "category_id": 18,
            "segmentation": [],
            "bbox": [
                87.95744680851062,
                154.3404255319149,
                66.38297872340426,
                19.914893617021285
            ],
            "ignore": 0,
            "iscrowd": 0,
            "area": 1322.0099592575834
        },
        {
            "id": 41,
            "image_id": 5,
            "category_id": 2,
            "segmentation": [],
            "bbox": [
                192.5106382978725,
                101.23404255319144,
                446.4255319148934,
                28.21276595744683
            ],
            "ignore": 0,
            "iscrowd": 0,
            "area": 12594.899049343598
        },
        {
            "id": 42,
            "image_id": 5,
            "category_id": 17,
            "segmentation": [],
            "bbox": [
                91.27659574468093,
                179.2340425531912,
                648.8936170212763,
                44.808510638298166
            ],
            "ignore": 0,
            "iscrowd": 0,
            "area": 29075.956541421638
        },
        {
            "id": 43,
            "image_id": 5,
            "category_id": 17,
            "segmentation": [],
            "bbox": [
                86.29787234042554,
                277.14893617021266,
                652.2127659574468,
                169.27659574468103
            ],
            "ignore": 0,
            "iscrowd": 0,
            "area": 110404.35672249898
        },
        {
            "id": 44,
            "image_id": 6,
            "category_id": 9,
            "segmentation": [],
            "bbox": [
                87.95744680851062,
                53.1063829787234,
                112.85106382978725,
                18.25531914893616
            ],
            "ignore": 0,
            "iscrowd": 0,
            "area": 2060.132186509732
        },
        {
            "id": 45,
            "image_id": 6,
            "category_id": 9,
            "segmentation": [],
            "bbox": [
                363.4468085106383,
                43.148936170212764,
                104.5531914893617,
                29.872340425531917
            ],
            "ignore": 0,
            "iscrowd": 0,
            "area": 3123.248528746039
        },
        {
            "id": 46,
            "image_id": 6,
            "category_id": 11,
            "segmentation": [],
            "bbox": [
                404.93617021276594,
                1072.085106382979,
                16.595744680851077,
                19.91489361702116
            ],
            "ignore": 0,
            "iscrowd": 0,
            "area": 330.502489814394
        },
        {
            "id": 47,
            "image_id": 6,
            "category_id": 11,
            "segmentation": [],
            "bbox": [
                683.7446808510639,
                54.765957446808514,
                56.4255319148936,
                18.25531914893617
            ],
            "ignore": 0,
            "iscrowd": 0,
            "area": 1030.066093254866
        },
        {
            "id": 48,
            "image_id": 6,
            "category_id": 17,
            "segmentation": [],
            "bbox": [
                91.27659574468085,
                86.29787234042553,
                648.8936170212767,
                957.5744680851063
            ],
            "ignore": 0,
            "iscrowd": 0,
            "area": 621363.9601629697
        },
        {
            "id": 49,
            "image_id": 7,
            "category_id": 9,
            "segmentation": [],
            "bbox": [
                87.95744680851062,
                53.1063829787234,
                112.85106382978725,
                18.25531914893616
            ],
            "ignore": 0,
            "iscrowd": 0,
            "area": 2060.132186509732
        },
        {
            "id": 50,
            "image_id": 7,
            "category_id": 9,
            "segmentation": [],
            "bbox": [
                363.4468085106383,
                43.148936170212764,
                104.5531914893617,
                29.872340425531917
            ],
            "ignore": 0,
            "iscrowd": 0,
            "area": 3123.248528746039
        },
        {
            "id": 51,
            "image_id": 7,
            "category_id": 11,
            "segmentation": [],
            "bbox": [
                404.93617021276594,
                1072.085106382979,
                16.595744680851077,
                19.91489361702116
            ],
            "ignore": 0,
            "iscrowd": 0,
            "area": 330.502489814394
        },
        {
            "id": 52,
            "image_id": 7,
            "category_id": 11,
            "segmentation": [],
            "bbox": [
                683.7446808510639,
                54.765957446808514,
                56.4255319148936,
                18.25531914893617
            ],
            "ignore": 0,
            "iscrowd": 0,
            "area": 1030.066093254866
        },
        {
            "id": 53,
            "image_id": 7,
            "category_id": 17,
            "segmentation": [],
            "bbox": [
                91.27659574468085,
                86.29787234042553,
                648.8936170212767,
                957.5744680851063
            ],
            "ignore": 0,
            "iscrowd": 0,
            "area": 621363.9601629697
        },
        {
            "id": 54,
            "image_id": 8,
            "category_id": 9,
            "segmentation": [],
            "bbox": [
                87.95744680851062,
                53.1063829787234,
                112.85106382978725,
                18.25531914893616
            ],
            "ignore": 0,
            "iscrowd": 0,
            "area": 2060.132186509732
        },
        {
            "id": 55,
            "image_id": 8,
            "category_id": 9,
            "segmentation": [],
            "bbox": [
                363.4468085106383,
                43.148936170212764,
                104.5531914893617,
                29.872340425531917
            ],
            "ignore": 0,
            "iscrowd": 0,
            "area": 3123.248528746039
        },
        {
            "id": 56,
            "image_id": 8,
            "category_id": 11,
            "segmentation": [],
            "bbox": [
                404.93617021276594,
                1072.085106382979,
                16.595744680851077,
                19.91489361702116
            ],
            "ignore": 0,
            "iscrowd": 0,
            "area": 330.502489814394
        },
        {
            "id": 57,
            "image_id": 8,
            "category_id": 11,
            "segmentation": [],
            "bbox": [
                683.7446808510639,
                54.765957446808514,
                56.4255319148936,
                18.25531914893617
            ],
            "ignore": 0,
            "iscrowd": 0,
            "area": 1030.066093254866
        },
        {
            "id": 58,
            "image_id": 8,
            "category_id": 17,
            "segmentation": [],
            "bbox": [
                91.27659574468088,
                86.29787234042553,
                648.8936170212766,
                866.2978723404257
            ],
            "ignore": 0,
            "iscrowd": 0,
            "area": 562135.1598008149
        },
        {
            "id": 59,
            "image_id": 8,
            "category_id": 18,
            "segmentation": [],
            "bbox": [
                87.95744680851062,
                972.5106382978723,
                74.68085106382979,
                19.914893617021324
            ],
            "ignore": 0,
            "iscrowd": 0,
            "area": 1487.261204164784
        },
        {
            "id": 60,
            "image_id": 8,
            "category_id": 6,
            "segmentation": [],
            "bbox": [
                89.61702127659574,
                997.4042553191489,
                650.5531914893617,
                49.787234042553145
            ],
            "ignore": 0,
            "iscrowd": 0,
            "area": 32389.24400181074
        },
        {
            "id": 61,
            "image_id": 9,
            "category_id": 9,
            "segmentation": [],
            "bbox": [
                87.95744680851062,
                53.1063829787234,
                112.85106382978725,
                18.25531914893616
            ],
            "ignore": 0,
            "iscrowd": 0,
            "area": 2060.132186509732
        },
        {
            "id": 62,
            "image_id": 9,
            "category_id": 9,
            "segmentation": [],
            "bbox": [
                363.4468085106383,
                43.148936170212764,
                104.5531914893617,
                29.872340425531917
            ],
            "ignore": 0,
            "iscrowd": 0,
            "area": 3123.248528746039
        },
        {
            "id": 63,
            "image_id": 9,
            "category_id": 11,
            "segmentation": [],
            "bbox": [
                404.93617021276594,
                1072.085106382979,
                16.595744680851077,
                19.91489361702116
            ],
            "ignore": 0,
            "iscrowd": 0,
            "area": 330.502489814394
        },
        {
            "id": 64,
            "image_id": 9,
            "category_id": 11,
            "segmentation": [],
            "bbox": [
                683.7446808510639,
                54.765957446808514,
                56.4255319148936,
                18.25531914893617
            ],
            "ignore": 0,
            "iscrowd": 0,
            "area": 1030.066093254866
        },
        {
            "id": 65,
            "image_id": 9,
            "category_id": 17,
            "segmentation": [],
            "bbox": [
                91.27659574468088,
                482.93617021276594,
                648.8936170212761,
                560.9361702127665
            ],
            "ignore": 0,
            "iscrowd": 0,
            "area": 363987.9004074242
        },
        {
            "id": 66,
            "image_id": 9,
            "category_id": 18,
            "segmentation": [],
            "bbox": [
                87.95744680851062,
                456.3829787234042,
                106.2127659574468,
                18.25531914893616
            ],
            "ignore": 0,
            "iscrowd": 0,
            "area": 1938.9479402444533
        },
        {
            "id": 67,
            "image_id": 9,
            "category_id": 6,
            "segmentation": [],
            "bbox": [
                91.27659574468085,
                86.29787234042553,
                647.2340425531916,
                345.19148936170205
            ],
            "ignore": 0,
            "iscrowd": 0,
            "area": 223419.68311453145
        },
        {
            "id": 68,
            "image_id": 10,
            "category_id": 9,
            "segmentation": [],
            "bbox": [
                87.95744680851062,
                53.1063829787234,
                112.85106382978725,
                18.25531914893616
            ],
            "ignore": 0,
            "iscrowd": 0,
            "area": 2060.132186509732
        },
        {
            "id": 69,
            "image_id": 10,
            "category_id": 9,
            "segmentation": [],
            "bbox": [
                363.4468085106383,
                43.148936170212764,
                104.5531914893617,
                29.872340425531917
            ],
            "ignore": 0,
            "iscrowd": 0,
            "area": 3123.248528746039
        },
        {
            "id": 70,
            "image_id": 10,
            "category_id": 11,
            "segmentation": [],
            "bbox": [
                404.93617021276594,
                1072.085106382979,
                16.595744680851077,
                19.91489361702116
            ],
            "ignore": 0,
            "iscrowd": 0,
            "area": 330.502489814394
        },
        {
            "id": 71,
            "image_id": 10,
            "category_id": 11,
            "segmentation": [],
            "bbox": [
                683.7446808510639,
                54.765957446808514,
                56.4255319148936,
                18.25531914893617
            ],
            "ignore": 0,
            "iscrowd": 0,
            "area": 1030.066093254866
        },
        {
            "id": 72,
            "image_id": 10,
            "category_id": 17,
            "segmentation": [],
            "bbox": [
                91.27659574468085,
                86.29787234042553,
                648.8936170212767,
                957.5744680851063
            ],
            "ignore": 0,
            "iscrowd": 0,
            "area": 621363.9601629697
        },
        {
            "id": 73,
            "image_id": 11,
            "category_id": 9,
            "segmentation": [],
            "bbox": [
                87.95744680851062,
                53.1063829787234,
                112.85106382978725,
                18.25531914893616
            ],
            "ignore": 0,
            "iscrowd": 0,
            "area": 2060.132186509732
        },
        {
            "id": 74,
            "image_id": 11,
            "category_id": 9,
            "segmentation": [],
            "bbox": [
                363.4468085106383,
                43.148936170212764,
                104.5531914893617,
                29.872340425531917
            ],
            "ignore": 0,
            "iscrowd": 0,
            "area": 3123.248528746039
        },
        {
            "id": 75,
            "image_id": 11,
            "category_id": 11,
            "segmentation": [],
            "bbox": [
                404.93617021276594,
                1072.085106382979,
                16.595744680851077,
                19.91489361702116
            ],
            "ignore": 0,
            "iscrowd": 0,
            "area": 330.502489814394
        },
        {
            "id": 76,
            "image_id": 11,
            "category_id": 11,
            "segmentation": [],
            "bbox": [
                683.7446808510639,
                54.765957446808514,
                56.4255319148936,
                18.25531914893617
            ],
            "ignore": 0,
            "iscrowd": 0,
            "area": 1030.066093254866
        },
        {
            "id": 77,
            "image_id": 11,
            "category_id": 17,
            "segmentation": [],
            "bbox": [
                91.27659574468085,
                86.29787234042553,
                648.8936170212767,
                957.5744680851063
            ],
            "ignore": 0,
            "iscrowd": 0,
            "area": 621363.9601629697
        },
        {
            "id": 78,
            "image_id": 12,
            "category_id": 9,
            "segmentation": [],
            "bbox": [
                87.95744680851062,
                53.1063829787234,
                112.85106382978725,
                18.25531914893616
            ],
            "ignore": 0,
            "iscrowd": 0,
            "area": 2060.132186509732
        },
        {
            "id": 79,
            "image_id": 12,
            "category_id": 9,
            "segmentation": [],
            "bbox": [
                363.4468085106383,
                43.148936170212764,
                104.5531914893617,
                29.872340425531917
            ],
            "ignore": 0,
            "iscrowd": 0,
            "area": 3123.248528746039
        },
        {
            "id": 80,
            "image_id": 12,
            "category_id": 11,
            "segmentation": [],
            "bbox": [
                404.93617021276594,
                1072.085106382979,
                16.595744680851077,
                19.91489361702116
            ],
            "ignore": 0,
            "iscrowd": 0,
            "area": 330.502489814394
        },
        {
            "id": 81,
            "image_id": 12,
            "category_id": 11,
            "segmentation": [],
            "bbox": [
                683.7446808510639,
                54.765957446808514,
                56.4255319148936,
                18.25531914893617
            ],
            "ignore": 0,
            "iscrowd": 0,
            "area": 1030.066093254866
        },
        {
            "id": 82,
            "image_id": 12,
            "category_id": 17,
            "segmentation": [],
            "bbox": [
                91.27659574468085,
                86.29787234042553,
                648.8936170212767,
                957.5744680851063
            ],
            "ignore": 0,
            "iscrowd": 0,
            "area": 621363.9601629697
        },
        {
            "id": 83,
            "image_id": 13,
            "category_id": 9,
            "segmentation": [],
            "bbox": [
                87.95744680851062,
                53.1063829787234,
                112.85106382978725,
                18.25531914893616
            ],
            "ignore": 0,
            "iscrowd": 0,
            "area": 2060.132186509732
        },
        {
            "id": 84,
            "image_id": 13,
            "category_id": 9,
            "segmentation": [],
            "bbox": [
                363.4468085106383,
                43.148936170212764,
                104.5531914893617,
                29.872340425531917
            ],
            "ignore": 0,
            "iscrowd": 0,
            "area": 3123.248528746039
        },
        {
            "id": 85,
            "image_id": 13,
            "category_id": 11,
            "segmentation": [],
            "bbox": [
                404.93617021276594,
                1072.085106382979,
                16.595744680851077,
                19.91489361702116
            ],
            "ignore": 0,
            "iscrowd": 0,
            "area": 330.502489814394
        },
        {
            "id": 86,
            "image_id": 13,
            "category_id": 11,
            "segmentation": [],
            "bbox": [
                683.7446808510639,
                54.765957446808514,
                56.4255319148936,
                18.25531914893617
            ],
            "ignore": 0,
            "iscrowd": 0,
            "area": 1030.066093254866
        },
        {
            "id": 87,
            "image_id": 13,
            "category_id": 17,
            "segmentation": [],
            "bbox": [
                91.27659574468085,
                86.29787234042553,
                648.8936170212767,
                957.5744680851063
            ],
            "ignore": 0,
            "iscrowd": 0,
            "area": 621363.9601629697
        },
        {
            "id": 88,
            "image_id": 14,
            "category_id": 9,
            "segmentation": [],
            "bbox": [
                87.95744680851062,
                53.1063829787234,
                112.85106382978725,
                18.25531914893616
            ],
            "ignore": 0,
            "iscrowd": 0,
            "area": 2060.132186509732
        },
        {
            "id": 89,
            "image_id": 14,
            "category_id": 9,
            "segmentation": [],
            "bbox": [
                363.4468085106383,
                43.148936170212764,
                104.5531914893617,
                29.872340425531917
            ],
            "ignore": 0,
            "iscrowd": 0,
            "area": 3123.248528746039
        },
        {
            "id": 90,
            "image_id": 14,
            "category_id": 11,
            "segmentation": [],
            "bbox": [
                404.93617021276594,
                1072.085106382979,
                16.595744680851077,
                19.91489361702116
            ],
            "ignore": 0,
            "iscrowd": 0,
            "area": 330.502489814394
        },
        {
            "id": 91,
            "image_id": 14,
            "category_id": 11,
            "segmentation": [],
            "bbox": [
                683.7446808510639,
                54.765957446808514,
                56.4255319148936,
                18.25531914893617
            ],
            "ignore": 0,
            "iscrowd": 0,
            "area": 1030.066093254866
        },
        {
            "id": 92,
            "image_id": 14,
            "category_id": 17,
            "segmentation": [],
            "bbox": [
                91.27659574468085,
                86.29787234042553,
                648.8936170212767,
                957.5744680851063
            ],
            "ignore": 0,
            "iscrowd": 0,
            "area": 621363.9601629697
        },
        {
            "id": 93,
            "image_id": 15,
            "category_id": 9,
            "segmentation": [],
            "bbox": [
                87.95744680851062,
                53.1063829787234,
                112.85106382978725,
                18.25531914893616
            ],
            "ignore": 0,
            "iscrowd": 0,
            "area": 2060.132186509732
        },
        {
            "id": 94,
            "image_id": 15,
            "category_id": 9,
            "segmentation": [],
            "bbox": [
                363.4468085106383,
                43.148936170212764,
                104.5531914893617,
                29.872340425531917
            ],
            "ignore": 0,
            "iscrowd": 0,
            "area": 3123.248528746039
        },
        {
            "id": 95,
            "image_id": 15,
            "category_id": 11,
            "segmentation": [],
            "bbox": [
                404.93617021276594,
                1072.085106382979,
                16.595744680851077,
                19.91489361702116
            ],
            "ignore": 0,
            "iscrowd": 0,
            "area": 330.502489814394
        },
        {
            "id": 96,
            "image_id": 15,
            "category_id": 11,
            "segmentation": [],
            "bbox": [
                683.7446808510639,
                54.765957446808514,
                56.4255319148936,
                18.25531914893617
            ],
            "ignore": 0,
            "iscrowd": 0,
            "area": 1030.066093254866
        },
        {
            "id": 97,
            "image_id": 15,
            "category_id": 17,
            "segmentation": [],
            "bbox": [
                91.27659574468085,
                86.29787234042553,
                648.8936170212767,
                957.5744680851063
            ],
            "ignore": 0,
            "iscrowd": 0,
            "area": 621363.9601629697
        },
        {
            "id": 98,
            "image_id": 16,
            "category_id": 9,
            "segmentation": [],
            "bbox": [
                87.95744680851062,
                53.1063829787234,
                112.85106382978725,
                18.25531914893616
            ],
            "ignore": 0,
            "iscrowd": 0,
            "area": 2060.132186509732
        },
        {
            "id": 99,
            "image_id": 16,
            "category_id": 9,
            "segmentation": [],
            "bbox": [
                363.4468085106383,
                43.148936170212764,
                104.5531914893617,
                29.872340425531917
            ],
            "ignore": 0,
            "iscrowd": 0,
            "area": 3123.248528746039
        },
        {
            "id": 100,
            "image_id": 16,
            "category_id": 11,
            "segmentation": [],
            "bbox": [
                404.93617021276594,
                1072.085106382979,
                16.595744680851077,
                19.91489361702116
            ],
            "ignore": 0,
            "iscrowd": 0,
            "area": 330.502489814394
        },
        {
            "id": 101,
            "image_id": 16,
            "category_id": 11,
            "segmentation": [],
            "bbox": [
                683.7446808510639,
                54.765957446808514,
                56.4255319148936,
                18.25531914893617
            ],
            "ignore": 0,
            "iscrowd": 0,
            "area": 1030.066093254866
        },
        {
            "id": 102,
            "image_id": 16,
            "category_id": 17,
            "segmentation": [],
            "bbox": [
                91.27659574468085,
                86.29787234042553,
                648.8936170212767,
                957.5744680851063
            ],
            "ignore": 0,
            "iscrowd": 0,
            "area": 621363.9601629697
        },
        {
            "id": 103,
            "image_id": 17,
            "category_id": 9,
            "segmentation": [],
            "bbox": [
                87.95744680851062,
                53.1063829787234,
                112.85106382978725,
                18.25531914893616
            ],
            "ignore": 0,
            "iscrowd": 0,
            "area": 2060.132186509732
        },
        {
            "id": 104,
            "image_id": 17,
            "category_id": 9,
            "segmentation": [],
            "bbox": [
                363.4468085106383,
                43.148936170212764,
                104.5531914893617,
                29.872340425531917
            ],
            "ignore": 0,
            "iscrowd": 0,
            "area": 3123.248528746039
        },
        {
            "id": 105,
            "image_id": 17,
            "category_id": 11,
            "segmentation": [],
            "bbox": [
                404.93617021276594,
                1072.085106382979,
                16.595744680851077,
                19.91489361702116
            ],
            "ignore": 0,
            "iscrowd": 0,
            "area": 330.502489814394
        },
        {
            "id": 106,
            "image_id": 17,
            "category_id": 11,
            "segmentation": [],
            "bbox": [
                683.7446808510639,
                54.765957446808514,
                56.4255319148936,
                18.25531914893617
            ],
            "ignore": 0,
            "iscrowd": 0,
            "area": 1030.066093254866
        },
        {
            "id": 107,
            "image_id": 17,
            "category_id": 17,
            "segmentation": [],
            "bbox": [
                91.27659574468085,
                86.29787234042553,
                648.8936170212767,
                957.5744680851063
            ],
            "ignore": 0,
            "iscrowd": 0,
            "area": 621363.9601629697
        },
        {
            "id": 108,
            "image_id": 18,
            "category_id": 9,
            "segmentation": [],
            "bbox": [
                87.95744680851062,
                53.1063829787234,
                112.85106382978725,
                18.25531914893616
            ],
            "ignore": 0,
            "iscrowd": 0,
            "area": 2060.132186509732
        },
        {
            "id": 109,
            "image_id": 18,
            "category_id": 9,
            "segmentation": [],
            "bbox": [
                363.4468085106383,
                43.148936170212764,
                104.5531914893617,
                29.872340425531917
            ],
            "ignore": 0,
            "iscrowd": 0,
            "area": 3123.248528746039
        },
        {
            "id": 110,
            "image_id": 18,
            "category_id": 11,
            "segmentation": [],
            "bbox": [
                404.93617021276594,
                1072.085106382979,
                16.595744680851077,
                19.91489361702116
            ],
            "ignore": 0,
            "iscrowd": 0,
            "area": 330.502489814394
        },
        {
            "id": 111,
            "image_id": 18,
            "category_id": 11,
            "segmentation": [],
            "bbox": [
                683.7446808510639,
                54.765957446808514,
                56.4255319148936,
                18.25531914893617
            ],
            "ignore": 0,
            "iscrowd": 0,
            "area": 1030.066093254866
        },
        {
            "id": 112,
            "image_id": 18,
            "category_id": 17,
            "segmentation": [],
            "bbox": [
                91.27659574468082,
                86.29787234042547,
                648.8936170212763,
                541.0212765957447
            ],
            "ignore": 0,
            "iscrowd": 0,
            "area": 351065.2530556811
        },
        {
            "id": 113,
            "image_id": 19,
            "category_id": 9,
            "segmentation": [],
            "bbox": [
                87.95744680851062,
                53.1063829787234,
                112.85106382978725,
                18.25531914893616
            ],
            "ignore": 0,
            "iscrowd": 0,
            "area": 2060.132186509732
        },
        {
            "id": 114,
            "image_id": 19,
            "category_id": 9,
            "segmentation": [],
            "bbox": [
                321.95744680851067,
                43.14893617021281,
                179.23404255319147,
                29.8723404255319
            ],
            "ignore": 0,
            "iscrowd": 0,
            "area": 5354.140334993206
        },
        {
            "id": 115,
            "image_id": 19,
            "category_id": 11,
            "segmentation": [],
            "bbox": [
                404.93617021276594,
                1072.085106382979,
                16.595744680851077,
                19.91489361702116
            ],
            "ignore": 0,
            "iscrowd": 0,
            "area": 330.502489814394
        },
        {
            "id": 116,
            "image_id": 19,
            "category_id": 11,
            "segmentation": [],
            "bbox": [
                683.7446808510639,
                54.765957446808514,
                56.4255319148936,
                18.25531914893617
            ],
            "ignore": 0,
            "iscrowd": 0,
            "area": 1030.066093254866
        },
        {
            "id": 117,
            "image_id": 19,
            "category_id": 5,
            "segmentation": [],
            "bbox": [
                91.27659574468093,
                86.29787234042551,
                648.8936170212767,
                305.3617021276595
            ],
            "ignore": 0,
            "iscrowd": 0,
            "area": 198147.25939339065
        },
        {
            "id": 118,
            "image_id": 19,
            "category_id": 9,
            "segmentation": [],
            "bbox": [
                474.63829787234033,
                56.42553191489362,
                26.55319148936178,
                4.978723404255321
            ],
            "ignore": 0,
            "iscrowd": 0,
            "area": 132.2009959257587
        },
        {
            "id": 119,
            "image_id": 19,
            "category_id": 5,
            "segmentation": [],
            "bbox": [
                87.95744680851062,
                408.25531914893617,
                643.9148936170211,
                567.5744680851062
            ],
            "ignore": 0,
            "iscrowd": 0,
            "area": 365469.6532367585
        },
        {
            "id": 120,
            "image_id": 20,
            "category_id": 9,
            "segmentation": [],
            "bbox": [
                87.95744680851062,
                53.1063829787234,
                112.85106382978725,
                18.25531914893616
            ],
            "ignore": 0,
            "iscrowd": 0,
            "area": 2060.132186509732
        },
        {
            "id": 121,
            "image_id": 20,
            "category_id": 9,
            "segmentation": [],
            "bbox": [
                318.6382978723402,
                43.1489361702128,
                199.1489361702128,
                29.87234042553191
            ],
            "ignore": 0,
            "iscrowd": 0,
            "area": 5949.044816659122
        },
        {
            "id": 122,
            "image_id": 20,
            "category_id": 11,
            "segmentation": [],
            "bbox": [
                404.93617021276594,
                1072.085106382979,
                16.595744680851077,
                19.91489361702116
            ],
            "ignore": 0,
            "iscrowd": 0,
            "area": 330.502489814394
        },
        {
            "id": 123,
            "image_id": 20,
            "category_id": 11,
            "segmentation": [],
            "bbox": [
                683.7446808510639,
                54.765957446808514,
                56.4255319148936,
                18.25531914893617
            ],
            "ignore": 0,
            "iscrowd": 0,
            "area": 1030.066093254866
        },
        {
            "id": 124,
            "image_id": 20,
            "category_id": 5,
            "segmentation": [],
            "bbox": [
                275.4893617021275,
                86.2978723404254,
                282.1276595744671,
                321.95744680851027
            ],
            "ignore": 0,
            "iscrowd": 0,
            "area": 90833.10095065598
        },
        {
            "id": 125,
            "image_id": 20,
            "category_id": 5,
            "segmentation": [],
            "bbox": [
                101.23404255319149,
                431.48936170212755,
                625.659574468085,
                333.57446808510633
            ],
            "ignore": 0,
            "iscrowd": 0,
            "area": 208704.05975554543
        },
        {
            "id": 126,
            "image_id": 20,
            "category_id": 5,
            "segmentation": [],
            "bbox": [
                101.23404255319149,
                781.6595744680852,
                627.3191489361702,
                169.27659574468078
            ],
            "ignore": 0,
            "iscrowd": 0,
            "area": 106190.44997736528
        },
        {
            "id": 127,
            "image_id": 21,
            "category_id": 9,
            "segmentation": [],
            "bbox": [
                87.95744680851062,
                53.1063829787234,
                112.85106382978725,
                18.25531914893616
            ],
            "ignore": 0,
            "iscrowd": 0,
            "area": 2060.132186509732
        },
        {
            "id": 128,
            "image_id": 21,
            "category_id": 9,
            "segmentation": [],
            "bbox": [
                318.6382978723402,
                43.1489361702128,
                199.1489361702128,
                29.87234042553191
            ],
            "ignore": 0,
            "iscrowd": 0,
            "area": 5949.044816659122
        },
        {
            "id": 129,
            "image_id": 21,
            "category_id": 11,
            "segmentation": [],
            "bbox": [
                404.93617021276594,
                1072.085106382979,
                16.595744680851077,
                19.91489361702116
            ],
            "ignore": 0,
            "iscrowd": 0,
            "area": 330.502489814394
        },
        {
            "id": 130,
            "image_id": 21,
            "category_id": 11,
            "segmentation": [],
            "bbox": [
                683.7446808510639,
                54.765957446808514,
                56.4255319148936,
                18.25531914893617
            ],
            "ignore": 0,
            "iscrowd": 0,
            "area": 1030.066093254866
        },
        {
            "id": 131,
            "image_id": 21,
            "category_id": 5,
            "segmentation": [],
            "bbox": [
                84.63829787234043,
                79.659574468085,
                648.8936170212761,
                743.4893617021281
            ],
            "ignore": 0,
            "iscrowd": 0,
            "area": 482445.50113173376
        },
        {
            "id": 132,
            "image_id": 22,
            "category_id": 9,
            "segmentation": [],
            "bbox": [
                87.95744680851062,
                53.1063829787234,
                112.85106382978725,
                18.25531914893616
            ],
            "ignore": 0,
            "iscrowd": 0,
            "area": 2060.132186509732
        },
        {
            "id": 133,
            "image_id": 22,
            "category_id": 9,
            "segmentation": [],
            "bbox": [
                318.6382978723402,
                43.1489361702128,
                199.1489361702128,
                29.87234042553191
            ],
            "ignore": 0,
            "iscrowd": 0,
            "area": 5949.044816659122
        },
        {
            "id": 134,
            "image_id": 22,
            "category_id": 11,
            "segmentation": [],
            "bbox": [
                404.93617021276594,
                1072.085106382979,
                16.595744680851077,
                19.91489361702116
            ],
            "ignore": 0,
            "iscrowd": 0,
            "area": 330.502489814394
        },
        {
            "id": 135,
            "image_id": 22,
            "category_id": 11,
            "segmentation": [],
            "bbox": [
                683.7446808510639,
                54.765957446808514,
                56.4255319148936,
                18.25531914893617
            ],
            "ignore": 0,
            "iscrowd": 0,
            "area": 1030.066093254866
        },
        {
            "id": 136,
            "image_id": 22,
            "category_id": 5,
            "segmentation": [],
            "bbox": [
                116.17021276595729,
                89.61702127659564,
                590.8085106382968,
                466.3404255319145
            ],
            "ignore": 0,
            "iscrowd": 0,
            "area": 275517.8922589399
        },
        {
            "id": 137,
            "image_id": 22,
            "category_id": 5,
            "segmentation": [],
            "bbox": [
                101.23404255319154,
                580.8510638297878,
                625.659574468085,
                448.0851063829781
            ],
            "ignore": 0,
            "iscrowd": 0,
            "area": 280348.7369850607
        }
    ],
    "info": {
        "year": 2025,
        "version": "1.0",
        "description": "",
        "contributor": "Label Studio",
        "url": "",
        "date_created": "2025-05-14 22:25:05.974896"
    }
}